comma/__init__.py
comma/_version.py
comma/lazy_loader.py
comma/main.py
comma/_personal/__init__.py
comma/_personal/lazy_install.py
comma/_personal/lazy_meetup.py
comma/_personal/server.py
comma/_personal/zero_tier.py
comma/command/__init__.py
comma/config/__init__.py
comma/devcon/__init__.py
comma/docker/__init__.py
comma/gum/__init__.py
comma/machine/__init__.py
comma/machine/local_machine.py
comma/machine/machine.py
comma/machine/ssh_machine.py
comma/misc/__init__.py
comma/misc/code.py
comma/misc/dual_writer.py
comma/misc/env_vars.py
comma/misc/file_utils.py
comma/misc/find_command.py
comma/misc/interactions.py
comma/misc/m_git.py
comma/misc/performance.py
comma/misc/singleton.py
comma/misc/tmux.py
comma/misc/wt.py
comma/resources/__init__.py
comma/resources/old__init__.py
comma/rich/__init__.py
comma/rich/halo.py
comma/shell_scripts/__init__.py
comma/shell_scripts/cmd.py
comma/shell_scripts/dev.sh
comma/shell_scripts/shell_scripts.py
comma/shell_scripts/shell_utils.py
comma/simple_argparser/__init__.py
comma/simple_argparser/simple_rick.py
comma/typer/__init__.py
comma/typer/pair.py
comma/typer/pair2.py
comma/typer/reflection.py
comma/typer/typer_utils.py
gron/__init__.py
gron/__main__.py
gum/__init__.py
comma_cli-2.0.6.dist-info/METADATA
comma_cli-2.0.6.dist-info/WHEEL
comma_cli-2.0.6.dist-info/entry_points.txt
comma_cli-2.0.6.dist-info/licenses/LICENSE.txt
comma_cli-2.0.6.dist-info/RECORD
