Metadata-Version: 2.3
Name: comma-cli
Version: 2.0.6
Summary: Multi-Tool
Project-URL: Documentation, https://github.com/FlavioAmurrioCS/comma-cli#readme
Project-URL: Issues, https://github.com/FlavioAmurrioCS/comma-cli/issues
Project-URL: Source, https://github.com/FlavioAmurrioCS/comma-cli
Author-email: Flavio Amurrio <25621374+FlavioAmurrioCS@users.noreply.github.com>
License-Expression: MIT
License-File: LICENSE.txt
Classifier: Development Status :: 4 - Beta
Classifier: Programming Language :: Python
Classifier: Programming Language :: Python :: 3.9
Classifier: Programming Language :: Python :: 3.10
Classifier: Programming Language :: Python :: 3.11
Classifier: Programming Language :: Python :: 3.12
Classifier: Programming Language :: Python :: Implementation :: CPython
Classifier: Programming Language :: Python :: Implementation :: PyPy
Requires-Python: >=3.9
Requires-Dist: persistent-cache-decorator
Requires-Dist: pyfunctional
Requires-Dist: requests
Requires-Dist: rich
Requires-Dist: runtool
Requires-Dist: typedfzf
Requires-Dist: typer
Requires-Dist: typing-extensions
Provides-Extra: personal
Requires-Dist: fastapi; extra == 'personal'
Requires-Dist: polyfactory; extra == 'personal'
Requires-Dist: pydantic; extra == 'personal'
Requires-Dist: selenium; extra == 'personal'
Requires-Dist: twilio; extra == 'personal'
Requires-Dist: uvicorn[standard]; extra == 'personal'
